tinfoil/__init__.py
tinfoil/client.py
tinfoil/github.py
tinfoil/sigstore.py
tinfoil/attestation/__init__.py
tinfoil/attestation/abi_sevsnp.py
tinfoil/attestation/attestation.py
tinfoil/attestation/genoa_cert_chain.py
tinfoil/attestation/validate.py
tinfoil/attestation/verify.py
tinfoil-0.10.1.dist-info/licenses/LICENSE
tinfoil-0.10.1.dist-info/METADATA
tinfoil-0.10.1.dist-info/WHEEL
tinfoil-0.10.1.dist-info/top_level.txt
tinfoil-0.10.1.dist-info/RECORD
