Metadata-Version: 2.4
Name: tinfoil
Version: 0.10.1
Summary: Python client for Tinfoil
Requires-Python: >=3.10
License-File: LICENSE
Requires-Dist: openai>=1.63.0
Requires-Dist: pybindgen>=0.22.0
Requires-Dist: httpx>=0.28
Requires-Dist: build>=1.2.0
Requires-Dist: requests>=2.31.0
Requires-Dist: cryptography>=42.0.0
Requires-Dist: pyOpenSSL>=25.0.0
Requires-Dist: sigstore>=4.1.0
Requires-Dist: platformdirs>=4.2.0
Requires-Dist: pytest-asyncio>=0.26.0
Dynamic: license-file
